{
  "generated_at": "2026-07-08 22:34:46",
  "source": "GitHub Actions / Tencent quote / cached financial and dividend data",
  "dividend_policy": "Current yield uses 2026 TTM available dividends; percentile history uses annual dividend for 2025 and before.",
  "rows": [
    {
      "code": "002958",
      "name": "青农商行",
      "listing_date": "2019-03-26",
      "price": 2.8,
      "dividend_yield": 0.08571428571428572,
      "dividend_yield_percentile": 1.0,
      "profit_growth": 0.05603178700338107,
      "profit_period": "20260331",
      "annual_dividend": 0.12,
      "ttm_dividend": 0.24,
      "updated_at": "2026-07-08 22:34:45",
      "error": "",
      "rank": 1
    },
    {
      "code": "600016",
      "name": "民生银行",
      "listing_date": "2000-12-19",
      "price": 3.33,
      "dividend_yield": 0.07537537537537538,
      "dividend_yield_percentile": 0.9983429991714996,
      "profit_growth": -0.09637419557369331,
      "profit_period": "20260331",
      "annual_dividend": 0.189,
      "ttm_dividend": 0.251,
      "updated_at": "2026-07-08 22:34:31",
      "error": "",
      "rank": 2
    },
    {
      "code": "601998",
      "name": "中信银行",
      "listing_date": "2007-04-27",
      "price": 7.2,
      "dividend_yield": 0.07683333333333332,
      "dividend_yield_percentile": 0.9892294946147473,
      "profit_growth": 0.03019119380798596,
      "profit_period": "20260331",
      "annual_dividend": 0.381,
      "ttm_dividend": 0.5531999999999999,
      "updated_at": "2026-07-08 22:34:35",
      "error": "",
      "rank": 3
    },
    {
      "code": "600926",
      "name": "杭州银行",
      "listing_date": "2016-10-27",
      "price": 15.4,
      "dividend_yield": 0.06103896103896103,
      "dividend_yield_percentile": 0.9776304888152444,
      "profit_growth": 0.10094037337577944,
      "profit_period": "20260331",
      "annual_dividend": 0.6599999999999999,
      "ttm_dividend": 0.94,
      "updated_at": "2026-07-08 22:34:37",
      "error": "",
      "rank": 4
    },
    {
      "code": "600036",
      "name": "招商银行",
      "listing_date": "2002-04-09",
      "price": 37.94,
      "dividend_yield": 0.0794148655772272,
      "dividend_yield_percentile": 0.9768019884009942,
      "profit_growth": 0.015179960306817675,
      "profit_period": "20260331",
      "annual_dividend": 2.016,
      "ttm_dividend": 3.013,
      "updated_at": "2026-07-08 22:34:31",
      "error": "",
      "rank": 5
    },
    {
      "code": "601860",
      "name": "紫金银行",
      "listing_date": "2019-01-03",
      "price": 2.5,
      "dividend_yield": 0.04,
      "dividend_yield_percentile": 0.9618889809444905,
      "profit_growth": 0.016181881982511692,
      "profit_period": "20260331",
      "annual_dividend": 0.1,
      "ttm_dividend": 0.1,
      "updated_at": "2026-07-08 22:34:41",
      "error": "",
      "rank": 6
    },
    {
      "code": "601997",
      "name": "贵阳银行",
      "listing_date": "2016-08-16",
      "price": 5.28,
      "dividend_yield": 0.056818181818181816,
      "dividend_yield_percentile": 0.9609958506224067,
      "profit_growth": 0.023705915251664766,
      "profit_period": "20260331",
      "annual_dividend": 0.3,
      "ttm_dividend": 0.3,
      "updated_at": "2026-07-08 22:34:43",
      "error": "",
      "rank": 7
    },
    {
      "code": "002936",
      "name": "郑州银行",
      "listing_date": "2018-09-19",
      "price": 1.7,
      "dividend_yield": 0.011764705882352941,
      "dividend_yield_percentile": 0.9419889502762431,
      "profit_growth": 0.05367022748330785,
      "profit_period": "20260331",
      "annual_dividend": 0.0,
      "ttm_dividend": 0.02,
      "updated_at": "2026-07-08 22:34:44",
      "error": "",
      "rank": 8
    },
    {
      "code": "002807",
      "name": "江阴银行",
      "listing_date": "2016-09-02",
      "price": 3.92,
      "dividend_yield": 0.05612244897959184,
      "dividend_yield_percentile": 0.9204639602319801,
      "profit_growth": 0.025011959078969026,
      "profit_period": "20260331",
      "annual_dividend": 0.22,
      "ttm_dividend": 0.22,
      "updated_at": "2026-07-08 22:34:43",
      "error": "",
      "rank": 9
    },
    {
      "code": "601128",
      "name": "常熟银行",
      "listing_date": "2016-09-30",
      "price": 6.09,
      "dividend_yield": 0.04433497536945813,
      "dividend_yield_percentile": 0.9113504556752279,
      "profit_growth": 0.1110241734799422,
      "profit_period": "20260331",
      "annual_dividend": 0.27,
      "ttm_dividend": 0.27,
      "updated_at": "2026-07-08 22:34:39",
      "error": "",
      "rank": 10
    },
    {
      "code": "603323",
      "name": "苏农银行",
      "listing_date": "2016-11-29",
      "price": 4.08,
      "dividend_yield": 0.051470588235294115,
      "dividend_yield_percentile": 0.908036454018227,
      "profit_growth": 0.05051368500503561,
      "profit_period": "20260331",
      "annual_dividend": 0.21,
      "ttm_dividend": 0.21,
      "updated_at": "2026-07-08 22:34:46",
      "error": "",
      "rank": 11
    },
    {
      "code": "600908",
      "name": "无锡银行",
      "listing_date": "2016-09-23",
      "price": 5.25,
      "dividend_yield": 0.04571428571428572,
      "dividend_yield_percentile": 0.9014084507042254,
      "profit_growth": 0.0273371790492134,
      "profit_period": "20260331",
      "annual_dividend": 0.24000000000000002,
      "ttm_dividend": 0.24000000000000002,
      "updated_at": "2026-07-08 22:34:36",
      "error": "",
      "rank": 12
    },
    {
      "code": "002839",
      "name": "张家港行",
      "listing_date": "2017-01-24",
      "price": 4.14,
      "dividend_yield": 0.053140096618357495,
      "dividend_yield_percentile": 0.8989229494614748,
      "profit_growth": 0.02504051048614664,
      "profit_period": "20260331",
      "annual_dividend": 0.22,
      "ttm_dividend": 0.22,
      "updated_at": "2026-07-08 22:34:43",
      "error": "",
      "rank": 13
    },
    {
      "code": "601818",
      "name": "光大银行",
      "listing_date": "2010-08-18",
      "price": 3.06,
      "dividend_yield": 0.06209150326797386,
      "dividend_yield_percentile": 0.8806959403479702,
      "profit_growth": -0.08063222079589216,
      "profit_period": "20260331",
      "annual_dividend": 0.10500000000000001,
      "ttm_dividend": 0.19,
      "updated_at": "2026-07-08 22:34:34",
      "error": "",
      "rank": 14
    },
    {
      "code": "002142",
      "name": "宁波银行",
      "listing_date": "2007-07-19",
      "price": 30.94,
      "dividend_yield": 0.0387847446670976,
      "dividend_yield_percentile": 0.8234804329725229,
      "profit_growth": 0.1030066064446542,
      "profit_period": "20260331",
      "annual_dividend": 0.3,
      "ttm_dividend": 1.2,
      "updated_at": "2026-07-08 22:34:36",
      "error": "",
      "rank": 15
    },
    {
      "code": "000001",
      "name": "平安银行",
      "listing_date": "1991-04-03",
      "price": 10.6,
      "dividend_yield": 0.05622641509433962,
      "dividend_yield_percentile": 0.7149958574979287,
      "profit_growth": 0.030292281498297324,
      "profit_period": "20260331",
      "annual_dividend": 0.596,
      "ttm_dividend": 0.596,
      "updated_at": "2026-07-08 22:34:29",
      "error": "",
      "rank": 16
    },
    {
      "code": "601398",
      "name": "工商银行",
      "listing_date": "2006-10-27",
      "price": 7.37,
      "dividend_yield": 0.06443690637720488,
      "dividend_yield_percentile": 0.704225352112676,
      "profit_growth": 0.03309330291363666,
      "profit_period": "20260331",
      "annual_dividend": 0.3103,
      "ttm_dividend": 0.4749,
      "updated_at": "2026-07-08 22:34:34",
      "error": "",
      "rank": 17
    },
    {
      "code": "600000",
      "name": "浦发银行",
      "listing_date": "1999-11-10",
      "price": 9.0,
      "dividend_yield": 0.04555555555555555,
      "dividend_yield_percentile": 0.6597510373443983,
      "profit_growth": 0.014944880100011382,
      "profit_period": "20260331",
      "annual_dividend": 0.0,
      "ttm_dividend": 0.41,
      "updated_at": "2026-07-08 22:34:30",
      "error": "",
      "rank": 18
    },
    {
      "code": "601166",
      "name": "兴业银行",
      "listing_date": "2007-02-05",
      "price": 17.21,
      "dividend_yield": 0.061940732132481115,
      "dividend_yield_percentile": 0.5824357912178956,
      "profit_growth": 0.001512859304084735,
      "profit_period": "20260331",
      "annual_dividend": 1.066,
      "ttm_dividend": 1.066,
      "updated_at": "2026-07-08 22:34:32",
      "error": "",
      "rank": 19
    },
    {
      "code": "600928",
      "name": "西安银行",
      "listing_date": "2019-03-01",
      "price": 3.52,
      "dividend_yield": 0.02840909090909091,
      "dividend_yield_percentile": 0.5211267605633803,
      "profit_growth": 0.06161998783695899,
      "profit_period": "20260331",
      "annual_dividend": 0.1,
      "ttm_dividend": 0.1,
      "updated_at": "2026-07-08 22:34:38",
      "error": "",
      "rank": 20
    },
    {
      "code": "601288",
      "name": "农业银行",
      "listing_date": "2010-07-15",
      "price": 6.16,
      "dividend_yield": 0.060876623376623376,
      "dividend_yield_percentile": 0.4780447390223695,
      "profit_growth": 0.04523779733355582,
      "profit_period": "20260331",
      "annual_dividend": 0.2495,
      "ttm_dividend": 0.375,
      "updated_at": "2026-07-08 22:34:33",
      "error": "",
      "rank": 21
    },
    {
      "code": "002966",
      "name": "苏州银行",
      "listing_date": "2019-08-02",
      "price": 7.4,
      "dividend_yield": 0.048648648648648644,
      "dividend_yield_percentile": 0.4407622203811102,
      "profit_growth": 0.0822713142417053,
      "profit_period": "20260331",
      "annual_dividend": 0.36,
      "ttm_dividend": 0.36,
      "updated_at": "2026-07-08 22:34:45",
      "error": "",
      "rank": 22
    },
    {
      "code": "601229",
      "name": "上海银行",
      "listing_date": "2016-11-16",
      "price": 9.07,
      "dividend_yield": 0.05733186328555678,
      "dividend_yield_percentile": 0.40430820215410107,
      "profit_growth": 0.006604672141608203,
      "profit_period": "20260331",
      "annual_dividend": 0.52,
      "ttm_dividend": 0.52,
      "updated_at": "2026-07-08 22:34:39",
      "error": "",
      "rank": 23
    },
    {
      "code": "601963",
      "name": "重庆银行",
      "listing_date": "2021-02-05",
      "price": 9.93,
      "dividend_yield": 0.04512588116817724,
      "dividend_yield_percentile": 0.35791217895608946,
      "profit_growth": 0.10400700382205752,
      "profit_period": "20260331",
      "annual_dividend": 0.4481,
      "ttm_dividend": 0.4481,
      "updated_at": "2026-07-08 22:34:42",
      "error": "",
      "rank": 24
    },
    {
      "code": "601009",
      "name": "南京银行",
      "listing_date": "2007-07-19",
      "price": 10.69,
      "dividend_yield": 0.04949953227315248,
      "dividend_yield_percentile": 0.30820215410107704,
      "profit_growth": 0.08046479609919643,
      "profit_period": "20260331",
      "annual_dividend": 0.52915,
      "ttm_dividend": 0.52915,
      "updated_at": "2026-07-08 22:34:31",
      "error": "",
      "rank": 25
    },
    {
      "code": "601916",
      "name": "浙商银行",
      "listing_date": "2019-11-26",
      "price": 2.75,
      "dividend_yield": 0.047636363636363636,
      "dividend_yield_percentile": 0.22530009233610343,
      "profit_growth": 0.007228105563960252,
      "profit_period": "20260331",
      "annual_dividend": 0.131,
      "ttm_dividend": 0.131,
      "updated_at": "2026-07-08 22:34:42",
      "error": "",
      "rank": 26
    },
    {
      "code": "601077",
      "name": "渝农商行",
      "listing_date": "2019-10-29",
      "price": 6.37,
      "dividend_yield": 0.05037833594976451,
      "dividend_yield_percentile": 0.2212096106048053,
      "profit_growth": 0.050719269610471684,
      "profit_period": "20260331",
      "annual_dividend": 0.32091,
      "ttm_dividend": 0.32091,
      "updated_at": "2026-07-08 22:34:38",
      "error": "",
      "rank": 27
    },
    {
      "code": "600015",
      "name": "华夏银行",
      "listing_date": "2003-09-12",
      "price": 6.8,
      "dividend_yield": 0.014705882352941178,
      "dividend_yield_percentile": 0.19138359569179786,
      "profit_growth": -0.015010863124629625,
      "profit_period": "20260331",
      "annual_dividend": 0.1,
      "ttm_dividend": 0.1,
      "updated_at": "2026-07-08 22:34:30",
      "error": "",
      "rank": 28
    },
    {
      "code": "601577",
      "name": "长沙银行",
      "listing_date": "2018-09-26",
      "price": 8.99,
      "dividend_yield": 0.02224694104560623,
      "dividend_yield_percentile": 0.17067108533554268,
      "profit_growth": 0.05774935978997897,
      "profit_period": "20260331",
      "annual_dividend": 0.2,
      "ttm_dividend": 0.2,
      "updated_at": "2026-07-08 22:34:40",
      "error": "",
      "rank": 29
    },
    {
      "code": "601187",
      "name": "厦门银行",
      "listing_date": "2020-10-27",
      "price": 6.96,
      "dividend_yield": 0.035919540229885055,
      "dividend_yield_percentile": 0.13173156586578294,
      "profit_growth": 0.07420087964045985,
      "profit_period": "20260331",
      "annual_dividend": 0.25,
      "ttm_dividend": 0.25,
      "updated_at": "2026-07-08 22:34:39",
      "error": "",
      "rank": 30
    },
    {
      "code": "002948",
      "name": "青岛银行",
      "listing_date": "2019-01-16",
      "price": 5.45,
      "dividend_yield": 0.03302752293577981,
      "dividend_yield_percentile": 0.10324729392173189,
      "profit_growth": 0.21155781370970184,
      "profit_period": "20260331",
      "annual_dividend": 0.18,
      "ttm_dividend": 0.18,
      "updated_at": "2026-07-08 22:34:44",
      "error": "",
      "rank": 31
    },
    {
      "code": "601169",
      "name": "北京银行",
      "listing_date": "2007-09-19",
      "price": 5.12,
      "dividend_yield": 0.0390625,
      "dividend_yield_percentile": 0.07870753935376967,
      "profit_growth": 0.055526590198123005,
      "profit_period": "20260331",
      "annual_dividend": 0.27799999999999997,
      "ttm_dividend": 0.2,
      "updated_at": "2026-07-08 22:34:32",
      "error": "",
      "rank": 32
    },
    {
      "code": "601838",
      "name": "成都银行",
      "listing_date": "2018-01-31",
      "price": 19.03,
      "dividend_yield": 0.04682080924855491,
      "dividend_yield_percentile": 0.058823529411764705,
      "profit_growth": 0.04808494899195792,
      "profit_period": "20260331",
      "annual_dividend": 0.921,
      "ttm_dividend": 0.891,
      "updated_at": "2026-07-08 22:34:41",
      "error": "",
      "rank": 33
    },
    {
      "code": "600919",
      "name": "江苏银行",
      "listing_date": "2016-08-02",
      "price": 11.46,
      "dividend_yield": 0.04758289703315881,
      "dividend_yield_percentile": 0.02236951118475559,
      "profit_growth": 0.08200989304400008,
      "profit_period": "20260331",
      "annual_dividend": 0.5641,
      "ttm_dividend": 0.5453,
      "updated_at": "2026-07-08 22:34:37",
      "error": "",
      "rank": 34
    },
    {
      "code": "601328",
      "name": "交通银行",
      "listing_date": "2007-05-15",
      "price": 6.77,
      "dividend_yield": 0.02308714918759232,
      "dividend_yield_percentile": 0.018227009113504555,
      "profit_growth": 0.031136686110673217,
      "profit_period": "20260331",
      "annual_dividend": 0.3247,
      "ttm_dividend": 0.1563,
      "updated_at": "2026-07-08 22:34:33",
      "error": "",
      "rank": 35
    },
    {
      "code": "601939",
      "name": "建设银行",
      "listing_date": "2007-09-25",
      "price": 10.07,
      "dividend_yield": 0.01845084409136048,
      "dividend_yield_percentile": 0.014084507042253521,
      "profit_growth": 0.035272522225288316,
      "profit_period": "20260331",
      "annual_dividend": 0.38870000000000005,
      "ttm_dividend": 0.18580000000000002,
      "updated_at": "2026-07-08 22:34:35",
      "error": "",
      "rank": 36
    },
    {
      "code": "601988",
      "name": "中国银行",
      "listing_date": "2006-07-05",
      "price": 5.92,
      "dividend_yield": 0.018479729729729732,
      "dividend_yield_percentile": 0.012427506213753107,
      "profit_growth": 0.04170038996394676,
      "profit_period": "20260331",
      "annual_dividend": 0.2263,
      "ttm_dividend": 0.10940000000000001,
      "updated_at": "2026-07-08 22:34:35",
      "error": "",
      "rank": 37
    },
    {
      "code": "601658",
      "name": "邮储银行",
      "listing_date": "2019-12-10",
      "price": 5.06,
      "dividend_yield": 0.02430830039525692,
      "dividend_yield_percentile": 0.007456503728251864,
      "profit_growth": 0.01901291293670293,
      "profit_period": "20260331",
      "annual_dividend": 0.2183,
      "ttm_dividend": 0.123,
      "updated_at": "2026-07-08 22:34:40",
      "error": "",
      "rank": 38
    }
  ]
}